inc_test_TB.v
/* task increment bug */


module inc_test_TB;

	reg clk;
	reg test_inc1;
	reg test_inc2;
	reg [3:0] count;
	wire [1:0] out1;
	wire [1:0] out2;

	inc_test counter_1( .clk(clk), .test_inc(test_inc1), .out(out1));

	inc_test counter_2( .clk(clk), .test_inc(test_inc2), .out(out2));

	initial	
	begin
$dumpfile("inc_test_tb.vcd");
$dumpvars(0,inc_test_TB);

		clk = 0;
		test_inc1 = 0;
		test_inc2 = 0;
		count = 0;
		#10;
	
		@(posedge clk);
		test_inc1 = 1'b1;
		@(posedge clk);
		test_inc1 = 1'b0;
		#40;
		

		$finish;
	end

	always @(posedge clk)
	begin
		count <= count + 1;
		if (count == 1)
		begin
			test_inc2 <= 1;
		end
		else
		begin
			test_inc2 <= 0;
		end
	end

		
	always // Clock generator
	begin
		begin
			#4 clk = !clk;
		end  
	end

endmodule    


module inc_test(clk, test_inc, out);

	input clk;
	input test_inc;
	output [1:0] out;


	reg [1:0] val;
	reg inc;

	wire [1:0] out = val;

	initial
	begin
		val = 0;
	end

	always @(posedge clk)
	begin
		if (test_inc)
		begin
			inc <= 1;
			@(negedge clk);
			inc <= 0;
		end
		else
			inc <= 0;
	end

	always @(posedge inc)
	begin
		val <= val + 1;
	end
endmodule

inc_test_tb.vcd
$date
	Sun May 28 09:27:46 2023
$end
$version
	Icarus Verilog
$end
$timescale
	1s
$end
$scope module inc_test_TB $end
$var wire 2 ! out2 [1:0] $end
$var wire 2 " out1 [1:0] $end
$var reg 1 # clk $end
$var reg 4 $ count [3:0] $end
$var reg 1 % test_inc1 $end
$var reg 1 & test_inc2 $end
$scope module counter_1 $end
$var wire 1 # clk $end
$var wire 2 ' out [1:0] $end
$var wire 1 % test_inc $end
$var reg 1 ( inc $end
$var reg 2 ) val [1:0] $end
$upscope $end
$scope module counter_2 $end
$var wire 1 # clk $end
$var wire 2 * out [1:0] $end
$var wire 1 & test_inc $end
$var reg 1 + inc $end
$var reg 2 , val [1:0] $end
$upscope $end
$upscope $end
$enddefinitions $end
$comment Show the parameter values. $end
$dumpall
$end
#0
$dumpvars
b0 ,
x+
b0 *
b0 )
x(
b0 '
0&
0%
b0 $
0#
b0 "
b0 !
$end
#4
0(
0+
b1 $
1#
#8
0#
#12
b1 "
b1 '
b1 )
1&
b10 $
1(
1%
1#
#16
0(
0#
#20
b1 !
b1 *
b1 ,
b10 "
b10 '
b10 )
1+
0&
b11 $
1(
0%
1#
#24
0(
0+
0#
#28
b100 $
1#
#32
0#
#36
b101 $
1#
#40
0#
#44
b110 $
1#
#48
0#
#52
b111 $
1#
#56
0#
#60
b1000 $
1#
