inc_test_TB.v
/* task increment bug */


module inc_test_TB;

	reg clk;
	reg test_inc1;
	reg test_inc2;
	reg [3:0] count;
	wire [1:0] out1;
	wire [1:0] out2;

	inc_test counter_1( .clk(clk), .test_inc(test_inc1), .out(out1));

	inc_test counter_2( .clk(clk), .test_inc(test_inc2), .out(out2));

	initial	
	begin
$dumpfile("inc_test_tb.vcd");
$dumpvars(0,inc_test_TB);

		clk = 0;
		test_inc1 = 0;
		test_inc2 = 0;
		count = 0;
		#7;
		@(negedge clk);
// 		$stop; // type trace on - cont
	
		// out1 is updated only twice in this loop
		for (integer i = 0 ; i < 8 ; i = i + 1)
		begin
			@(posedge clk);
			test_inc1 = 1'b1;
			@(posedge clk);
			test_inc1 = 1'b0;
		end
	
		// out1 is updated the expected 8 times if zero length delays are added
		for (integer j = 0 ; j < 8 ; j = j + 1)
		begin
			@(posedge clk);
			#0 test_inc1 = 1'b1;
			@(posedge clk);
			#0 test_inc1 = 1'b0;
		end

		@(negedge clk);
//		$stop; // type trace off - cont
		#40;
		

		$finish;
	end

	always @(posedge clk)
	begin
		count <= count + 1;
		if ((count % 2) == 1)
		begin
			test_inc2 <= 1;
		end
		else
		begin
			test_inc2 <= 0;
		end
	end

		
	always // Clock generator
	begin
		begin
			#4 clk = !clk;
		end  
	end

endmodule    


module inc_test(clk, test_inc, out);

	input clk;
	input test_inc;
	output [1:0] out;


	reg [1:0] val;
	reg inc;

	wire [1:0] out = val;

	initial
	begin
		val = 0;
	end

	always @(posedge clk)
	begin
		if (test_inc)
		begin
			inc <= 1;
			@(negedge clk);
			inc <= 0;
		end
		else
			inc <= 0;
	end

	always @(posedge inc)
	begin
		val <= val + 1;
	end
endmodule

inc_test_tb.vcd
$date
	Mon Jun 26 21:15:35 2023
$end
$version
	Icarus Verilog
$end
$timescale
	1s
$end
$scope module inc_test_TB $end
$var wire 2 ! out2 [1:0] $end
$var wire 2 " out1 [1:0] $end
$var reg 1 # clk $end
$var reg 4 $ count [3:0] $end
$var reg 1 % test_inc1 $end
$var reg 1 & test_inc2 $end
$scope module counter_1 $end
$var wire 1 # clk $end
$var wire 2 ' out [1:0] $end
$var wire 1 % test_inc $end
$var reg 1 ( inc $end
$var reg 2 ) val [1:0] $end
$upscope $end
$scope module counter_2 $end
$var wire 1 # clk $end
$var wire 2 * out [1:0] $end
$var wire 1 & test_inc $end
$var reg 1 + inc $end
$var reg 2 , val [1:0] $end
$upscope $end
$scope begin $ivl_for_loop0 $end
$var integer 32 - i [31:0] $end
$upscope $end
$scope begin $ivl_for_loop1 $end
$var integer 32 . j [31:0] $end
$upscope $end
$upscope $end
$enddefinitions $end
$comment Show the parameter values. $end
$dumpall
$end
#0
$dumpvars
bx .
bx -
b0 ,
x+
b0 *
b0 )
x(
b0 '
0&
0%
b0 $
0#
b0 "
b0 !
$end
#4
0(
0+
b1 $
1#
#8
b0 -
0#
#12
b1 "
b1 '
b1 )
1&
b10 $
1(
1%
1#
#16
0(
0#
#20
b1 !
b1 *
b1 ,
b10 "
b10 '
b10 )
1+
0&
b11 $
1(
b1 -
0%
1#
#24
0(
0+
0#
#28
1&
b100 $
1%
1#
#32
0#
#36
b10 !
b10 *
b10 ,
1+
0&
b101 $
b10 -
0%
1#
#40
0+
0#
#44
1&
b110 $
1%
1#
#48
0#
#52
b11 !
b11 *
b11 ,
1+
0&
b111 $
b11 -
0%
1#
#56
0+
0#
#60
1&
b1000 $
1%
1#
#64
0#
#68
b0 !
b0 *
b0 ,
1+
0&
b1001 $
b100 -
0%
1#
#72
0+
0#
#76
1&
b1010 $
1%
1#
#80
0#
#84
b1 !
b1 *
b1 ,
1+
0&
b1011 $
b101 -
0%
1#
#88
0+
0#
#92
1&
b1100 $
1%
1#
#96
0#
#100
b10 !
b10 *
b10 ,
1+
0&
b1101 $
b110 -
0%
1#
#104
0+
0#
#108
1&
b1110 $
1%
1#
#112
0#
#116
b11 !
b11 *
b11 ,
1+
0&
b1111 $
b111 -
0%
1#
#120
0+
0#
#124
1&
b0 $
1%
1#
#128
0#
#132
b0 !
b0 *
b0 ,
1+
0&
b1 $
b0 .
b1000 -
0%
1#
#136
0+
0#
#140
1&
b10 $
1%
1#
#144
0#
#148
b1 !
b1 *
b1 ,
b11 "
b11 '
b11 )
1+
1(
0&
b11 $
b1 .
0%
1#
#152
0(
0+
0#
#156
1&
b100 $
1%
1#
#160
0#
#164
b0 "
b0 '
b0 )
b10 !
b10 *
b10 ,
1(
1+
0&
b101 $
b10 .
0%
1#
#168
0+
0(
0#
#172
1&
b110 $
1%
1#
#176
0#
#180
b11 !
b11 *
b11 ,
b1 "
b1 '
b1 )
1+
1(
0&
b111 $
b11 .
0%
1#
#184
0(
0+
0#
#188
1&
b1000 $
1%
1#
#192
0#
#196
b10 "
b10 '
b10 )
b0 !
b0 *
b0 ,
1(
1+
0&
b1001 $
b100 .
0%
1#
#200
0+
0(
0#
#204
1&
b1010 $
1%
1#
#208
0#
#212
b1 !
b1 *
b1 ,
b11 "
b11 '
b11 )
1+
1(
0&
b1011 $
b101 .
0%
1#
#216
0(
0+
0#
#220
1&
b1100 $
1%
1#
#224
0#
#228
b0 "
b0 '
b0 )
b10 !
b10 *
b10 ,
1(
1+
0&
b1101 $
b110 .
0%
1#
#232
0+
0(
0#
#236
1&
b1110 $
1%
1#
#240
0#
#244
b11 !
b11 *
b11 ,
b1 "
b1 '
b1 )
1+
1(
0&
b1111 $
b111 .
0%
1#
#248
0(
0+
0#
#252
1&
b0 $
1%
1#
#256
0#
#260
b10 "
b10 '
b10 )
b0 !
b0 *
b0 ,
1(
1+
0&
b1 $
b1000 .
0%
1#
#264
0+
0(
0#
#268
1&
b10 $
1#
#272
0#
#276
b1 !
b1 *
b1 ,
1+
0&
b11 $
1#
#280
0+
0#
#284
1&
b100 $
1#
#288
0#
#292
b10 !
b10 *
b10 ,
1+
0&
b101 $
1#
#296
0+
0#
#300
1&
b110 $
1#
